sctriangulate/433colorhex.txt
sctriangulate/__init__.py
sctriangulate/artifact_genes.txt
sctriangulate/colors.py
sctriangulate/logger.py
sctriangulate/main_class.py
sctriangulate/metrics.py
sctriangulate/preprocessing.py
sctriangulate/prune.py
sctriangulate/shapley.py
sctriangulate/spatial.py
sctriangulate/viewer.py
sctriangulate/viewer/inspection.css
sctriangulate/viewer/inspection.js
sctriangulate/viewer/viewer.css
sctriangulate/viewer/viewer.js
sctriangulate-0.13.0.dist-info/LICENSE
sctriangulate-0.13.0.dist-info/METADATA
sctriangulate-0.13.0.dist-info/WHEEL
sctriangulate-0.13.0.dist-info/top_level.txt
sctriangulate-0.13.0.dist-info/RECORD
