Metadata-Version: 2.1
Name: sctriangulate
Version: 0.13.0
Summary: A Python package to mix-and-match conflicting clustering results in single cell analysis, and generate reconciled clustering solutions.
Home-page: https://github.com/frankligy/scTriangulate
Author: Guangyuan(Frank) Li
Author-email: li2g2@mail.uc.edu
Maintainer: Guangyuan(Frank) Li
Maintainer-email: li2g2@mail.uc.edu
License: UNKNOWN
Project-URL: Ducumentation, https://sctriangulate.readthedocs.io
Platform: UNKNOWN
Classifier: Development Status :: 3 - Alpha
Classifier: Programming Language :: Python :: 3
Classifier: License :: OSI Approved :: BSD License
Classifier: Operating System :: OS Independent
Requires-Python: >=3.7
Requires-Dist: squidpy (==1.2.0)
Requires-Dist: gseapy (==0.10.4)
Requires-Dist: scrublet (==0.2.3)
Requires-Dist: yattag
Requires-Dist: anytree
Requires-Dist: mygene (==3.2.2)
